qassure/__init__.py
qassure/framework.py
qassure-0.1.0.dist-info/LICENSE
qassure-0.1.0.dist-info/METADATA
qassure-0.1.0.dist-info/WHEEL
qassure-0.1.0.dist-info/top_level.txt
qassure-0.1.0.dist-info/RECORD
