Metadata-Version: 2.1
Name: qassure
Version: 0.1.0
Summary: Audit any data and report on deficiencies
Home-page: https://github.com/turnbullerin/qassure
Author: Erin Turnbull
Author-email: erin.a.turnbull@gmail.com
Project-URL: Bug Tracker, https://github.com/turnbullerin/qassure/issues
Project-URL: Documentation, https://qassure.readthedocs.io/en/latest/
Classifier: Programming Language :: Python :: 3
Classifier: License :: OSI Approved :: MIT License
Classifier: Operating System :: OS Independent
Requires-Python: >=3.7
License-File: LICENSE
